{"is_source_file": true, "format": "JavaScript (React JSX)", "description": "The file defines the main React application component, setting up routing, authentication flow, and layout components like Header and pages such as Login, Signup, and Prompt.", "external_files": ["./components/Header", "./pages/Login", "./pages/Signup", "./pages/Prompt", "./hooks/useAuth", "./App.css"], "external_methods": ["useAuthProvider"], "published": ["App"], "classes": [], "methods": [{"name": "RequireAuth({ isAuthenticated, children })", "description": "Component that enforces authentication by redirecting unauthenticated users to the login page.", "scope": "", "scopeKind": ""}, {"name": "App()", "scope": "", "scopeKind": "", "description": "unavailable"}, {"name": "AuthApp()", "scope": "", "scopeKind": "", "description": "unavailable"}], "calls": ["useAuthProvider()", "auth.logout", "auth.setToken", "Navigate", "Header", "Login", "Signup", "Prompt", "RequireAuth"], "search-terms": ["React", "Routing", "Authentication", "App.js", "Header", "Login", "Signup", "Prompt", "useAuthProvider"], "state": 2, "file_id": 10, "knowledge_revision": 28, "git_revision": "fb5648c935431a0395379956f946abcc6c7cea5e", "revision_history": [{"25": "fb5648c935431a0395379956f946abcc6c7cea5e"}, {"28": "fb5648c935431a0395379956f946abcc6c7cea5e"}], "ctags": [{"_type": "tag", "name": "App", "path": "/home/kavia/workspace/code-generation/natural-query-processing-platform-96847-96857/dsp_frontend/src/App.js", "pattern": "/^function App() {$/", "language": "JavaScript", "kind": "function", "signature": "()"}, {"_type": "tag", "name": "AuthApp", "path": "/home/kavia/workspace/code-generation/natural-query-processing-platform-96847-96857/dsp_frontend/src/App.js", "pattern": "/^function AuthApp() {$/", "language": "JavaScript", "kind": "function", "signature": "()"}, {"_type": "tag", "name": "RequireAuth", "path": "/home/kavia/workspace/code-generation/natural-query-processing-platform-96847-96857/dsp_frontend/src/App.js", "pattern": "/^function RequireAuth({ isAuthenticated, children }) {$/", "language": "JavaScript", "kind": "function", "signature": "({ isAuthenticated, children })"}, {"_type": "tag", "name": "auth", "path": "/home/kavia/workspace/code-generation/natural-query-processing-platform-96847-96857/dsp_frontend/src/App.js", "pattern": "/^              <RequireAuth isAuthenticated={auth.isAuthenticated}>$/", "language": "JavaScript", "kind": "field", "scope": "AuthApp.AnonymousClasse133f3c40101", "scopeKind": "class"}], "hash": "42747fc348ce95664430a67f24dc9f87", "format-version": 4, "code-base-name": "dsp_frontend", "filename": "dsp_frontend/src/App.js", "fields": [{"name": "<RequireAuth isAuthenticated={auth.isAuthenticated}>", "scope": "AuthApp.AnonymousClasse133f3c40101", "scopeKind": "class", "description": "unavailable"}]}